Workbook
Name IQ_CH: 110000
Name IQ_CQ: 5000
Name IQ_CY: 10000
Name IQ_DAILY: 500000
Name IQ_FH: 100000
Name IQ_FQ: 500
Name IQ_FY: 1000
Name IQ_LTM: 2000
Name IQ_MONTH: 15000
Name IQ_NTM: 6000
Name IQ_WEEK: 50000
Name IQ_YTD: 3000
Name UPDATE: 'Data Sheet'!$E$1

Sheet Financials>
B2: =" Historical Financial Statement-" & 'Data Sheet'!B1 -> Historical Financial Statement-INFOSYS LTD
B3: Years | C3: ='Data Sheet'!B16 -> 42825 | D3: ='Data Sheet'!C16 -> 43190 | E3: ='Data Sheet'!D16 -> 43555 | F3: ='Data Sheet'!E16 -> 43921 | G3: ='Data Sheet'!F16 -> 44286 | H3: ='Data Sheet'!G16 -> 44651 | I3: ='Data Sheet'!H16 -> 45016 | J3: ='Data Sheet'!I16 -> 45382 | ... L3: ='Data Sheet'!K16 -> 46112 | M3: LTM
A4: # | B4: Income Statement
B5: Sales | C5: =IFERROR('Data Sheet'!B17,0) -> 68484 | D5: =IFERROR('Data Sheet'!C17,0) -> 70522 | E5: =IFERROR('Data Sheet'!D17,0) -> 82675 | F5: =IFERROR('Data Sheet'!E17,0) -> 90791 | G5: =IFERROR('Data Sheet'!F17,0) -> 100472 | H5: =IFERROR('Data Sheet'!G17,0) -> 121641 | I5: =IFERROR('Data Sheet'!H17,0) -> 146767 | J5: =IFERROR('Data Sheet'!I17,0) -> 153670 | ... L5: =IFERROR('Data Sheet'!K17,0) -> 178650 | M5: =IFERROR(SUM('Data Sheet'!H42:K42),0) -> 178650
B6: Sales Growth | C6: - | D6: =D5/C5-1 -> 0.029758776 | E6: =E5/D5-1 -> 0.1723292 | F6: =F5/E5-1 -> 0.098167523 | G6: =G5/F5-1 -> 0.10662951 | H6: =H5/G5-1 -> 0.21069552 | I6: =I5/H5-1 -> 0.20655864 | J6: =J5/I5-1 -> 0.047033734 | K6: =K5/J5-1 -> 0.060649444 | ... M6: =M5/L5-1 -> 0
B8: COGS | C8: =IFERROR(SUM('Data Sheet'!B18,'Data Sheet'!B20:B22)-1*'Data Sheet'!B19,) -> 44609 | D8: =IFERROR(SUM('Data Sheet'!C18,'Data Sheet'!C20:C22)-1*'Data Sheet'!C19,) -> 46395 | E8: =IFERROR(SUM('Data Sheet'!D18,'Data Sheet'!D20:D22)-1*'Data Sheet'!D19,) -> 55446 | F8: =IFERROR(SUM('Data Sheet'!E18,'Data Sheet'!E20:E22)-1*'Data Sheet'!E19,) -> 62210 | G8: =IFERROR(SUM('Data Sheet'!F18,'Data Sheet'!F20:F22)-1*'Data Sheet'!F19,) -> 68490 | H8: =IFERROR(SUM('Data Sheet'!G18,'Data Sheet'!G20:G22)-1*'Data Sheet'!G19,) -> 84819 | I8: =IFERROR(SUM('Data Sheet'!H18,'Data Sheet'!H20:H22)-1*'Data Sheet'!H19,) -> 104880 | J8: =IFERROR(SUM('Data Sheet'!I18,'Data Sheet'!I20:I22)-1*'Data Sheet'!I19,) -> 110030 | ... L8: =IFERROR(SUM('Data Sheet'!K18,'Data Sheet'!K20:K22)-1*'Data Sheet'!K19,) -> 128257 | M8: =IFERROR(SUM('Data Sheet'!H43:K43),0) -> 136371
B9: COGS % Sales | C9: =C8/C5 -> 0.65137842 | D9: =D8/D5 -> 0.65787981 | E9: =E8/E5 -> 0.67065014 | F9: =F8/F5 -> 0.68520007 | G9: =G8/G5 -> 0.68168246 | H9: =H8/H5 -> 0.69728957 | I9: =I8/I5 -> 0.71460206 | J9: =J8/J5 -> 0.71601484 | ... M9: =M8/M5 -> 0.76334173
B11: Gross Profit | C11: =C5-C8 -> 23875 | D11: =D5-D8 -> 24127 | E11: =E5-E8 -> 27229 | F11: =F5-F8 -> 28581 | G11: =G5-G8 -> 31982 | H11: =H5-H8 -> 36822 | I11: =I5-I8 -> 41887 | J11: =J5-J8 -> 43640 | ... M11: =M5-M8 -> 42279
B12: Gross Margin | C12: =C11/C5 -> 0.34862158 | D12: =D11/D5 -> 0.34212019 | E12: =E11/E5 -> 0.32934986 | F12: =F11/F5 -> 0.31479993 | G12: =G11/G5 -> 0.31831754 | H12: =H11/H5 -> 0.30271043 | I12: =I11/I5 -> 0.28539794 | J12: =J11/J5 -> 0.28398516 | ... M12: =M11/M5 -> 0.23665827
B14: Selling & General Expenses | C14: =IFERROR(SUM('Data Sheet'!B23:B24),0) -> 5271 | D14: =IFERROR(SUM('Data Sheet'!C23:C24),0) -> 5305 | E14: =IFERROR(SUM('Data Sheet'!D23:D24),0) -> 7059 | F14: =IFERROR(SUM('Data Sheet'!E23:E24),0) -> 6314 | G14: =IFERROR(SUM('Data Sheet'!F23:F24),0) -> 4093 | H14: =IFERROR(SUM('Data Sheet'!G23:G24),0) -> 5331 | I14: =IFERROR(SUM('Data Sheet'!H23:H24),0) -> 6757 | J14: =IFERROR(SUM('Data Sheet'!I23:I24),0) -> 7215 | ... L14: =IFERROR(SUM('Data Sheet'!K23:K24),0) -> 8113
B15: S&G Exp % Sales | C15: =C14/C5 -> 0.076966883 | D15: =D14/D5 -> 0.075224753 | E15: =E14/E5 -> 0.085382522 | F15: =F14/F5 -> 0.069544338 | G15: =G14/G5 -> 0.040737718 | H15: =H14/H5 -> 0.043825684 | I15: =I14/I5 -> 0.04603896 | J15: =J14/J5 -> 0.046951259 | ... L15: =L14/L5 -> 0.045412818
B17: EBITDA | C17: =C11-C14 -> 18604 | D17: =D11-D14 -> 18822 | E17: =E11-E14 -> 20170 | F17: =F11-F14 -> 22267 | G17: =G11-G14 -> 27889 | H17: =H11-H14 -> 31491 | I17: =I11-I14 -> 35130 | J17: =J11-J14 -> 36425 | ... L17: =L11-L14 -> 42280 | M17: =IFERROR(SUM('Data Sheet'!H51:K51),0) -> 45278
B18: EBITDA Margins | C18: =C17/C5 -> 0.27165469 | D18: =D17/D5 -> 0.26689544 | E18: =E17/E5 -> 0.24396734 | F18: =F17/F5 -> 0.24525559 | G18: =G17/G5 -> 0.27757982 | H18: =H17/H5 -> 0.25888475 | I18: =I17/I5 -> 0.23935898 | J18: =J17/J5 -> 0.2370339 | ... M18: =M17/M5 -> 0.25344528
B20: Interest | C20: =IFERROR('Data Sheet'!B27,0) -> 0 | D20: =IFERROR('Data Sheet'!C27,0) -> 0 | E20: =IFERROR('Data Sheet'!D27,0) -> 0 | F20: =IFERROR('Data Sheet'!E27,0) -> 170 | G20: =IFERROR('Data Sheet'!F27,0) -> 195 | H20: =IFERROR('Data Sheet'!G27,0) -> 200 | I20: =IFERROR('Data Sheet'!H27,0) -> 284 | J20: =IFERROR('Data Sheet'!I27,0) -> 470 | ... L20: =IFERROR('Data Sheet'!K27,0) -> 416 | M20: =IFERROR(SUM('Data Sheet'!H46:K46),0) -> 416
B21: Interest % Sales | C21: =C20/C5 -> 0 | D21: =D20/D5 -> 0 | E21: =E20/E5 -> 0 | F21: =F20/F5 -> 0.0018724323 | G21: =G20/G5 -> 0.0019408392 | H21: =H20/H5 -> 0.0016441825 | I21: =I20/I5 -> 0.0019350399 | J21: =J20/J5 -> 0.003058502 | ... M21: =M20/M5 -> 0.0023285754
B23: Depreciation | C23: =IFERROR('Data Sheet'!B26,0) -> 1703 | D23: =IFERROR('Data Sheet'!C26,0) -> 1863 | E23: =IFERROR('Data Sheet'!D26,0) -> 2011 | F23: =IFERROR('Data Sheet'!E26,0) -> 2893 | G23: =IFERROR('Data Sheet'!F26,0) -> 3267 | H23: =IFERROR('Data Sheet'!G26,0) -> 3476 | I23: =IFERROR('Data Sheet'!H26,0) -> 4225 | J23: =IFERROR('Data Sheet'!I26,0) -> 4678 | ... L23: =IFERROR('Data Sheet'!K26,0) -> 4902 | M23: =IFERROR(SUM('Data Sheet'!H45:K45),0) -> 4901
B24: Depreciation%Sales | C24: =C23/C5 -> 0.024867122 | D24: =D23/D5 -> 0.026417288 | E24: =E23/E5 -> 0.024324161 | F24: =F23/F5 -> 0.031864392 | G24: =G23/G5 -> 0.032516522 | H24: =H23/H5 -> 0.028575891 | I24: =I23/I5 -> 0.028787125 | J24: =J23/J5 -> 0.030441856 | ... M24: =M23/M5 -> 0.027433529 | Q24: =Q15-(Q18+Q21) -> 0
B26: Earnings Before Tax | C26: =C17-(C20+C23) -> 16901 | D26: =D17-(D20+D23) -> 16959 | E26: =E17-(E20+E23) -> 18159 | F26: =F17-(F20+F23) -> 19204 | G26: =G17-(G20+G23) -> 24427 | H26: =H17-(H20+H23) -> 27815 | I26: =I17-(I20+I23) -> 30621 | J26: =J17-(J20+J23) -> 31277 | ... M26: =M17-(M20+M23) -> 39961
B27: EBT % Sales | C27: =C26/C5 -> 0.24678757 | D27: =D26/D5 -> 0.24047815 | E27: =E26/E5 -> 0.21964318 | F27: =F26/F5 -> 0.21151876 | G27: =G26/G5 -> 0.24312246 | H27: =H26/H5 -> 0.22866468 | I27: =I26/I5 -> 0.20863682 | J27: =J26/J5 -> 0.20353355 | ... M27: =M26/M5 -> 0.22368318
B29: Tax | C29: =IFERROR('Data Sheet'!B29,0) -> 5598 | D29: =IFERROR('Data Sheet'!C29,0) -> 4241 | E29: =IFERROR('Data Sheet'!D29,0) -> 5631 | F29: =IFERROR('Data Sheet'!E29,0) -> 5368 | G29: =IFERROR('Data Sheet'!F29,0) -> 7205 | H29: =IFERROR('Data Sheet'!G29,0) -> 7964 | I29: =IFERROR('Data Sheet'!H29,0) -> 9214 | J29: =IFERROR('Data Sheet'!I29,0) -> 9740 | ... L29: =IFERROR('Data Sheet'!K29,0) -> 10521 | M29: =IFERROR(SUM('Data Sheet'!H48:K48),0) -> 10521
B30: Effective Tax Rate | C30: =C29/C26 -> 0.331223 | D30: =D29/D26 -> 0.25007371 | E30: =E29/E26 -> 0.31009417 | F30: =F29/F26 -> 0.2795251 | G30: =G29/G26 -> 0.29496049 | H30: =H29/H26 -> 0.28632033 | I30: =I29/I26 -> 0.30090461 | J30: =J29/J26 -> 0.31141094 | ... M30: =M29/M26 -> 0.2632817
B32: Net Profit | C32: =C26-C29 -> 11303 | D32: =D26-D29 -> 12718 | E32: =E26-E29 -> 12528 | F32: =F26-F29 -> 13836 | G32: =G26-G29 -> 17222 | H32: =H26-H29 -> 19851 | I32: =I26-I29 -> 21407 | J32: =J26-J29 -> 21537 | ... M32: =M26-M29 -> 29440
B33: Net Margins | C33: =C32/C5 -> 0.16504585 | D33: =D32/D5 -> 0.18034089 | E33: =E32/E5 -> 0.15153311 | F33: =F32/F5 -> 0.15239396 | G33: =G32/G5 -> 0.17141094 | H33: =H32/H5 -> 0.16319333 | I33: =I32/I5 -> 0.14585704 | J33: =J32/J5 -> 0.14015097 | ... M33: =M32/M5 -> 0.16479149
B35: No of Equity Shares | C35: =IFERROR('Data Sheet'!B93,0) -> 459.39 | D35: =IFERROR('Data Sheet'!C93,0) -> 436.82 | E35: =IFERROR('Data Sheet'!D93,0) -> 436.89 | F35: =IFERROR('Data Sheet'!E93,0) -> 425.9 | G35: =IFERROR('Data Sheet'!F93,0) -> 426.07 | H35: =IFERROR('Data Sheet'!G93,0) -> 420.67 | I35: =IFERROR('Data Sheet'!H93,0) -> 414.86 | J35: =IFERROR('Data Sheet'!I93,0) -> 415.09 | ... M35: =IFERROR('Data Sheet'!L93,0) -> 0
B36: In crores
B37: EPS | C37: =C32/C35 -> 24.604367 | D37: =D32/D35 -> 29.114967 | E37: =E32/E35 -> 28.67541 | F37: =F32/F35 -> 32.486499 | G37: =G32/G35 -> 40.420588 | H37: =H32/H35 -> 47.189008 | I37: =I32/I35 -> 51.60054 | J37: =J32/J35 -> 51.885133 | ... L37: =L32/L35 -> 65.196272 | M37: -
B38: EPS Growth % | D38: =D37/C37-1 -> 0.18332521 | E38: =E37/D37-1 -> -0.015097286 | F38: =F37/E37-1 -> 0.13290442 | G38: =G37/F37-1 -> 0.24422727 | H38: =H37/G37-1 -> 0.16744981 | I38: =I37/H37-1 -> 0.093486431 | J38: =J37/I37-1 -> 0.0055153183 | K38: =K37/J37-1 -> 0.074273236 | L38: =L37/K37-1 -> 0.16967463 | M38: -
B40: Dividend per Share | C40: =IFERROR('Data Sheet'!B31/'Data Sheet'!B93,0) -> 12.824833 | D40: =IFERROR('Data Sheet'!C31/'Data Sheet'!C93,0) -> 21.669337 | E40: =IFERROR('Data Sheet'!D31/'Data Sheet'!D93,0) -> 21.109433 | F40: =IFERROR('Data Sheet'!E31/'Data Sheet'!E93,0) -> 17.438366 | G40: =IFERROR('Data Sheet'!F31/'Data Sheet'!F93,0) -> 26.91952 | H40: =IFERROR('Data Sheet'!G31/'Data Sheet'!G93,0) -> 30.92115 | I40: =IFERROR('Data Sheet'!H31/'Data Sheet'!H93,0) -> 33.913127 | J40: =IFERROR('Data Sheet'!I31/'Data Sheet'!I93,0) -> 45.901371 | ... L40: =IFERROR('Data Sheet'!K31/'Data Sheet'!K93,0) -> 47.91005 | M40: -
B41: Dividend payout ratio | C41: =C40/C37 -> 0.52124215 | D41: =D40/D37 -> 0.74426797 | E41: =E40/E37 -> 0.73615102 | F41: =F40/F37 -> 0.53678809 | G41: =G40/G37 -> 0.66598537 | H41: =H40/H37 -> 0.6552617 | I41: =I40/I37 -> 0.65722427 | J41: =J40/J37 -> 0.88467289 | ... L41: =L40/L37 -> 0.73485874 | M41: =-G44 -> 0
B43: Retained Earnings | C43: =IFERROR(IF(C37>C40,1-C41,0),0) -> 0.47875785 | D43: =IFERROR(IF(D37>D40,1-D41,0),0) -> 0.25573203 | E43: =IFERROR(IF(E37>E40,1-E41,0),0) -> 0.26384898 | F43: =IFERROR(IF(F37>F40,1-F41,0),0) -> 0.46321191 | G43: =IFERROR(IF(G37>G40,1-G41,0),0) -> 0.33401463 | H43: =IFERROR(IF(H37>H40,1-H41,0),0) -> 0.3447383 | I43: =IFERROR(IF(I37>I40,1-I41,0),0) -> 0.34277573 | J43: =IFERROR(IF(J37>J40,1-J41,0),0) -> 0.11532711 | ... M43: =IFERROR(IF(M37>M40,1-M41,0),0) -> 0
A46: # | B46: Balance Sheet
B47: Equity Share Capital | C47: =IFERROR('Data Sheet'!B57,0) -> 1144 | D47: =IFERROR('Data Sheet'!C57,0) -> 1088 | E47: =IFERROR('Data Sheet'!D57,0) -> 2170 | F47: =IFERROR('Data Sheet'!E57,0) -> 2122 | G47: =IFERROR('Data Sheet'!F57,0) -> 2124 | H47: =IFERROR('Data Sheet'!G57,0) -> 2098 | I47: =IFERROR('Data Sheet'!H57,0) -> 2069 | J47: =IFERROR('Data Sheet'!I57,0) -> 2071 | ... L47: =IFERROR('Data Sheet'!K57,0) -> 2024
B48: Reserves | C48: =IFERROR('Data Sheet'!B58,0) -> 67838 | D48: =IFERROR('Data Sheet'!C58,0) -> 63835 | E48: =IFERROR('Data Sheet'!D58,0) -> 62778 | F48: =IFERROR('Data Sheet'!E58,0) -> 63328 | G48: =IFERROR('Data Sheet'!F58,0) -> 74227 | H48: =IFERROR('Data Sheet'!G58,0) -> 73252 | I48: =IFERROR('Data Sheet'!H58,0) -> 73338 | J48: =IFERROR('Data Sheet'!I58,0) -> 86045 | ... L48: =IFERROR('Data Sheet'!K58,0) -> 90828
B49: Borrowings | C49: =IFERROR('Data Sheet'!B59,0) -> 0 | D49: =IFERROR('Data Sheet'!C59,0) -> 0 | E49: =IFERROR('Data Sheet'!D59,0) -> 0 | F49: =IFERROR('Data Sheet'!E59,0) -> 4633 | G49: =IFERROR('Data Sheet'!F59,0) -> 5325 | H49: =IFERROR('Data Sheet'!G59,0) -> 5474 | I49: =IFERROR('Data Sheet'!H59,0) -> 8299 | J49: =IFERROR('Data Sheet'!I59,0) -> 8359 | ... L49: =IFERROR('Data Sheet'!K59,0) -> 9176
B50: Other Liabilities | C50: =IFERROR('Data Sheet'!B60,0) -> 14166 | D50: =IFERROR('Data Sheet'!C60,0) -> 14426 | E50: =IFERROR('Data Sheet'!D60,0) -> 19118 | F50: =IFERROR('Data Sheet'!E60,0) -> 21717 | G50: =IFERROR('Data Sheet'!F60,0) -> 25835 | H50: =IFERROR('Data Sheet'!G60,0) -> 35905 | I50: =IFERROR('Data Sheet'!H60,0) -> 40890 | J50: =IFERROR('Data Sheet'!I60,0) -> 40885 | ... L50: =IFERROR('Data Sheet'!K60,0) -> 52260
B51: Total Liabilities | C51: =IFERROR('Data Sheet'!B61,0) -> 83148 | D51: =IFERROR('Data Sheet'!C61,0) -> 79349 | E51: =IFERROR('Data Sheet'!D61,0) -> 84066 | F51: =IFERROR('Data Sheet'!E61,0) -> 91800 | G51: =IFERROR('Data Sheet'!F61,0) -> 107511 | H51: =IFERROR('Data Sheet'!G61,0) -> 116729 | I51: =IFERROR('Data Sheet'!H61,0) -> 124596 | J51: =IFERROR('Data Sheet'!I61,0) -> 137360 | ... L51: =IFERROR('Data Sheet'!K61,0) -> 154288
B53: Fixed Assests Net Block | C53: =IFERROR('Data Sheet'!B62,0) -> 14179 | D53: =IFERROR('Data Sheet'!C62,0) -> 12574 | E53: =IFERROR('Data Sheet'!D62,0) -> 15710 | F53: =IFERROR('Data Sheet'!E62,0) -> 23789 | G53: =IFERROR('Data Sheet'!F62,0) -> 25505 | H53: =IFERROR('Data Sheet'!G62,0) -> 25800 | I53: =IFERROR('Data Sheet'!H62,0) -> 29225 | J53: =IFERROR('Data Sheet'!I62,0) -> 27622 | ... L53: =IFERROR('Data Sheet'!K62,0) -> 33770
B54: Capital Work in Progress | C54: =IFERROR('Data Sheet'!B63,0) -> 1365 | D54: =IFERROR('Data Sheet'!C63,0) -> 1606 | E54: =IFERROR('Data Sheet'!D63,0) -> 1388 | F54: =IFERROR('Data Sheet'!E63,0) -> 954 | G54: =IFERROR('Data Sheet'!F63,0) -> 922 | H54: =IFERROR('Data Sheet'!G63,0) -> 416 | I54: =IFERROR('Data Sheet'!H63,0) -> 288 | J54: =IFERROR('Data Sheet'!I63,0) -> 293 | ... L54: =IFERROR('Data Sheet'!K63,0) -> 526
B55: Investments | C55: =IFERROR('Data Sheet'!B64,0) -> 16423 | D55: =IFERROR('Data Sheet'!C64,0) -> 12163 | E55: =IFERROR('Data Sheet'!D64,0) -> 11261 | F55: =IFERROR('Data Sheet'!E64,0) -> 8792 | G55: =IFERROR('Data Sheet'!F64,0) -> 14205 | H55: =IFERROR('Data Sheet'!G64,0) -> 20324 | I55: =IFERROR('Data Sheet'!H64,0) -> 19478 | J55: =IFERROR('Data Sheet'!I64,0) -> 24623 | ... L55: =IFERROR('Data Sheet'!K64,0) -> 21880
B56: Other Assets | C56: =IFERROR('Data Sheet'!B65-SUM('Data Sheet'!B67:B69,0),0) -> 16234 | D56: =IFERROR('Data Sheet'!C65-SUM('Data Sheet'!C67:C69,0),0) -> 20046 | E56: =IFERROR('Data Sheet'!D65-SUM('Data Sheet'!D67:D69,0),0) -> 21312 | F56: =IFERROR('Data Sheet'!E65-SUM('Data Sheet'!E67:E69,0),0) -> 21129 | G56: =IFERROR('Data Sheet'!F65-SUM('Data Sheet'!F67:F69,0),0) -> 22871 | H56: =IFERROR('Data Sheet'!G65-SUM('Data Sheet'!G67:G69,0),0) -> 30019 | I56: =IFERROR('Data Sheet'!H65-SUM('Data Sheet'!H67:H69,0),0) -> 38008 | J56: =IFERROR('Data Sheet'!I65-SUM('Data Sheet'!I67:I69,0),0) -> 39843 | ... L56: =IFERROR('Data Sheet'!K65-SUM('Data Sheet'!K67:K69,0),0) -> 40677
B57: Total Non Current Assests | C57: =IFERROR(SUM(C53:C56),0) -> 48201 | D57: =IFERROR(SUM(D53:D56),0) -> 46389 | E57: =IFERROR(SUM(E53:E56),0) -> 49671 | F57: =IFERROR(SUM(F53:F56),0) -> 54664 | G57: =IFERROR(SUM(G53:G56),0) -> 63503 | H57: =IFERROR(SUM(H53:H56),0) -> 76559 | I57: =IFERROR(SUM(I53:I56),0) -> 86999 | J57: =IFERROR(SUM(J53:J56),0) -> 92381 | ... L57: =IFERROR(SUM(L53:L56),0) -> 96853
B59: Receivables | C59: =IFERROR('Data Sheet'!B67,0) -> 12322 | D59: =IFERROR('Data Sheet'!C67,0) -> 13142 | E59: =IFERROR('Data Sheet'!D67,0) -> 14827 | F59: =IFERROR('Data Sheet'!E67,0) -> 18487 | G59: =IFERROR('Data Sheet'!F67,0) -> 19294 | H59: =IFERROR('Data Sheet'!G67,0) -> 22698 | I59: =IFERROR('Data Sheet'!H67,0) -> 25424 | J59: =IFERROR('Data Sheet'!I67,0) -> 30193 | ... L59: =IFERROR('Data Sheet'!K67,0) -> 35234
B60: Inventory | C60: =IFERROR('Data Sheet'!B68,0) -> 0 | D60: =IFERROR('Data Sheet'!C68,0) -> 0 | E60: =IFERROR('Data Sheet'!D68,0) -> 0 | F60: =IFERROR('Data Sheet'!E68,0) -> 0 | G60: =IFERROR('Data Sheet'!F68,0) -> 0 | H60: =IFERROR('Data Sheet'!G68,0) -> 0 | I60: =IFERROR('Data Sheet'!H68,0) -> 0 | J60: =IFERROR('Data Sheet'!I68,0) -> 0 | ... L60: =IFERROR('Data Sheet'!K68,0) -> 0
B61: Cash & Bank | C61: =IFERROR('Data Sheet'!B69,0) -> 22625 | D61: =IFERROR('Data Sheet'!C69,0) -> 19818 | E61: =IFERROR('Data Sheet'!D69,0) -> 19568 | F61: =IFERROR('Data Sheet'!E69,0) -> 18649 | G61: =IFERROR('Data Sheet'!F69,0) -> 24714 | H61: =IFERROR('Data Sheet'!G69,0) -> 17472 | I61: =IFERROR('Data Sheet'!H69,0) -> 12173 | J61: =IFERROR('Data Sheet'!I69,0) -> 14786 | ... L61: =IFERROR('Data Sheet'!K69,0) -> 22201
B62: Total Current Assests | C62: =IFERROR(SUM(C59:C61,0),0) -> 34947 | D62: =IFERROR(SUM(D59:D61,0),0) -> 32960 | E62: =IFERROR(SUM(E59:E61,0),0) -> 34395 | F62: =IFERROR(SUM(F59:F61,0),0) -> 37136 | G62: =IFERROR(SUM(G59:G61,0),0) -> 44008 | H62: =IFERROR(SUM(H59:H61,0),0) -> 40170 | I62: =IFERROR(SUM(I59:I61,0),0) -> 37597 | J62: =IFERROR(SUM(J59:J61,0),0) -> 44979 | ... L62: =IFERROR(SUM(L59:L61,0),0) -> 57435
B64: Total Assests | C64: =C57+C62 -> 83148 | D64: =D57+D62 -> 79349 | E64: =E57+E62 -> 84066 | F64: =F57+F62 -> 91800 | G64: =G57+G62 -> 107511 | H64: =H57+H62 -> 116729 | I64: =I57+I62 -> 124596 | J64: =J57+J62 -> 137360 | ... L64: =L57+L62 -> 154288
B66: Check | C66: =C64=C51 -> TRUE | D66: =D64=D51 -> TRUE | E66: =E64=E51 -> TRUE | F66: =F64=F51 -> TRUE | G66: =G64=G51 -> TRUE | H66: =H64=H51 -> TRUE | I66: =I64=I51 -> TRUE | J66: =J64=J51 -> TRUE | ... L66: =L64=L51 -> TRUE
A68: # | B68: Cashflow statement
B69: Operating Activites
B70: Profit from operations | C70: =IFERROR('Cash Flow Data'!E4,0) -> 24406 | D70: =IFERROR('Cash Flow Data'!F4,0) -> 36303 | E70: =IFERROR('Cash Flow Data'!G4,0) -> 43397 | F70: =IFERROR('Cash Flow Data'!H4,0) -> 38626 | G70: =IFERROR('Cash Flow Data'!I4,0) -> 28840 | H70: =IFERROR('Cash Flow Data'!J4,0) -> 33312 | I70: =IFERROR('Cash Flow Data'!K4,0) -> 28771 | J70: =IFERROR('Cash Flow Data'!L4,0) -> 23352 | ... L70: =IFERROR('Cash Flow Data'!N4,0) -> 26666
B71: Receivables | C71: =IFERROR('Cash Flow Data'!E5,0) -> -5177 | D71: =IFERROR('Cash Flow Data'!F5,0) -> 445 | E71: =IFERROR('Cash Flow Data'!G5,0) -> -3179 | F71: =IFERROR('Cash Flow Data'!H5,0) -> -2223 | G71: =IFERROR('Cash Flow Data'!I5,0) -> -4152 | H71: =IFERROR('Cash Flow Data'!J5,0) -> -10688 | I71: =IFERROR('Cash Flow Data'!K5,0) -> -9109 | J71: =IFERROR('Cash Flow Data'!L5,0) -> 9950 | ... L71: =IFERROR('Cash Flow Data'!N5,0) -> 337
B72: Inventory | C72: =IFERROR('Cash Flow Data'!E6,0) -> -2656 | D72: =IFERROR('Cash Flow Data'!F6,0) -> -2853 | E72: =IFERROR('Cash Flow Data'!G6,0) -> -3692 | F72: =IFERROR('Cash Flow Data'!H6,0) -> -5743 | G72: =IFERROR('Cash Flow Data'!I6,0) -> -6621 | H72: =IFERROR('Cash Flow Data'!J6,0) -> -3560 | I72: =IFERROR('Cash Flow Data'!K6,0) -> 2069 | J72: =IFERROR('Cash Flow Data'!L6,0) -> 2326 | ... L72: =IFERROR('Cash Flow Data'!N6,0) -> 597
B73: Payables | C73: =IFERROR('Cash Flow Data'!E7,0) -> 8132 | D73: =IFERROR('Cash Flow Data'!F7,0) -> 4694 | E73: =IFERROR('Cash Flow Data'!G7,0) -> 3598 | F73: =IFERROR('Cash Flow Data'!H7,0) -> 3947 | G73: =IFERROR('Cash Flow Data'!I7,0) -> 9301 | H73: =IFERROR('Cash Flow Data'!J7,0) -> 7320 | I73: =IFERROR('Cash Flow Data'!K7,0) -> -4692 | J73: =IFERROR('Cash Flow Data'!L7,0) -> -8085 | ... L73: =IFERROR('Cash Flow Data'!N7,0) -> -7012
B74: Loans Advances | C74: =IFERROR('Cash Flow Data'!E8,0) -> 0 | D74: =IFERROR('Cash Flow Data'!F8,0) -> 0 | E74: =IFERROR('Cash Flow Data'!G8,0) -> 0 | F74: =IFERROR('Cash Flow Data'!H8,0) -> -520 | G74: =IFERROR('Cash Flow Data'!I8,0) -> 0 | H74: =IFERROR('Cash Flow Data'!J8,0) -> 0 | I74: =IFERROR('Cash Flow Data'!K8,0) -> 0 | J74: =IFERROR('Cash Flow Data'!L8,0) -> 0 | ... L74: =IFERROR('Cash Flow Data'!N8,0) -> 0
B75: Other WC items | C75: =IFERROR('Cash Flow Data'!E9,0) -> -303 | D75: =IFERROR('Cash Flow Data'!F9,0) -> 1870 | E75: =IFERROR('Cash Flow Data'!G9,0) -> -398 | F75: =IFERROR('Cash Flow Data'!H9,0) -> 5852 | G75: =IFERROR('Cash Flow Data'!I9,0) -> 4727 | H75: =IFERROR('Cash Flow Data'!J9,0) -> 494 | I75: =IFERROR('Cash Flow Data'!K9,0) -> 4512 | J75: =IFERROR('Cash Flow Data'!L9,0) -> 875 | ... L75: =IFERROR('Cash Flow Data'!N9,0) -> -4396
B76: Working capital changes | C76: =IFERROR('Cash Flow Data'!E10,0) -> -3 | D76: =IFERROR('Cash Flow Data'!F10,0) -> 4157 | E76: =IFERROR('Cash Flow Data'!G10,0) -> -3672 | F76: =IFERROR('Cash Flow Data'!H10,0) -> 1313 | G76: =IFERROR('Cash Flow Data'!I10,0) -> 3254 | H76: =IFERROR('Cash Flow Data'!J10,0) -> -6434 | I76: =IFERROR('Cash Flow Data'!K10,0) -> -7221 | J76: =IFERROR('Cash Flow Data'!L10,0) -> 5065 | ... L76: =IFERROR('Cash Flow Data'!N10,0) -> -10474
B77: Direct taxes | C77: =IFERROR('Cash Flow Data'!E11,0) -> -2240 | D77: =IFERROR('Cash Flow Data'!F11,0) -> -4308 | E77: =IFERROR('Cash Flow Data'!G11,0) -> -4194 | F77: =IFERROR('Cash Flow Data'!H11,0) -> -2040 | G77: =IFERROR('Cash Flow Data'!I11,0) -> -1895 | H77: =IFERROR('Cash Flow Data'!J11,0) -> -3021 | I77: =IFERROR('Cash Flow Data'!K11,0) -> -2659 | J77: =IFERROR('Cash Flow Data'!L11,0) -> -1785 | ... L77: =IFERROR('Cash Flow Data'!N11,0) -> -1910
B78: Cash from Operating Activity | C78: =SUM(C70:C77) -> 22159 | D78: =SUM(D70:D77) -> 40308 | E78: =SUM(E70:E77) -> 31860 | F78: =SUM(F70:F77) -> 39212 | G78: =SUM(G70:G77) -> 33454 | H78: =SUM(H70:H77) -> 17423 | I78: =SUM(I70:I77) -> 11671 | J78: =SUM(J70:J77) -> 31698 | ... L78: =SUM(L70:L77) -> 3808
B80: Investing Activities
B81: Fixed assets purchased | C81: =IFERROR('Cash Flow Data'!E13,0) -> -18863 | D81: =IFERROR('Cash Flow Data'!F13,0) -> -26975 | E81: =IFERROR('Cash Flow Data'!G13,0) -> -31962 | F81: =IFERROR('Cash Flow Data'!H13,0) -> -31503 | G81: =IFERROR('Cash Flow Data'!I13,0) -> -16072 | H81: =IFERROR('Cash Flow Data'!J13,0) -> -35079 | I81: =IFERROR('Cash Flow Data'!K13,0) -> -35304 | J81: =IFERROR('Cash Flow Data'!L13,0) -> -29702 | ... L81: =IFERROR('Cash Flow Data'!N13,0) -> -15168
B82: Fixed assets sold | C82: =IFERROR('Cash Flow Data'!E14,0) -> 37 | D82: =IFERROR('Cash Flow Data'!F14,0) -> 50 | E82: =IFERROR('Cash Flow Data'!G14,0) -> 74 | F82: =IFERROR('Cash Flow Data'!H14,0) -> 59 | G82: =IFERROR('Cash Flow Data'!I14,0) -> 53 | H82: =IFERROR('Cash Flow Data'!J14,0) -> 30 | I82: =IFERROR('Cash Flow Data'!K14,0) -> 67 | J82: =IFERROR('Cash Flow Data'!L14,0) -> 171 | ... L82: =IFERROR('Cash Flow Data'!N14,0) -> 230
B83: Investments purchased | C83: =IFERROR('Cash Flow Data'!E15,0) -> 73 | D83: =IFERROR('Cash Flow Data'!F15,0) -> -429 | E83: =IFERROR('Cash Flow Data'!G15,0) -> -5461 | F83: =IFERROR('Cash Flow Data'!H15,0) -> -4728 | G83: =IFERROR('Cash Flow Data'!I15,0) -> -6 | H83: =IFERROR('Cash Flow Data'!J15,0) -> -329 | I83: =IFERROR('Cash Flow Data'!K15,0) -> -130 | J83: =IFERROR('Cash Flow Data'!L15,0) -> -1439 | ... L83: =IFERROR('Cash Flow Data'!N15,0) -> -3008
B84: Investments sold | C84: =IFERROR('Cash Flow Data'!E16,0) -> 34 | D84: =IFERROR('Cash Flow Data'!F16,0) -> 4 | E84: =IFERROR('Cash Flow Data'!G16,0) -> 42 | F84: =IFERROR('Cash Flow Data'!H16,0) -> 89 | G84: =IFERROR('Cash Flow Data'!I16,0) -> 1965 | H84: =IFERROR('Cash Flow Data'!J16,0) -> 2381 | I84: =IFERROR('Cash Flow Data'!K16,0) -> 5644 | J84: =IFERROR('Cash Flow Data'!L16,0) -> 21 | ... L84: =IFERROR('Cash Flow Data'!N16,0) -> 104
B85: Interest received | C85: =IFERROR('Cash Flow Data'!E17,0) -> 713 | D85: =IFERROR('Cash Flow Data'!F17,0) -> 653 | E85: =IFERROR('Cash Flow Data'!G17,0) -> 698 | F85: =IFERROR('Cash Flow Data'!H17,0) -> 731 | G85: =IFERROR('Cash Flow Data'!I17,0) -> 638 | H85: =IFERROR('Cash Flow Data'!J17,0) -> 690 | I85: =IFERROR('Cash Flow Data'!K17,0) -> 761 | J85: =IFERROR('Cash Flow Data'!L17,0) -> 1104 | ... L85: =IFERROR('Cash Flow Data'!N17,0) -> 653
B86: Dividends received | C86: =IFERROR('Cash Flow Data'!E18,0) -> 95 | D86: =IFERROR('Cash Flow Data'!F18,0) -> 40 | E86: =IFERROR('Cash Flow Data'!G18,0) -> 80 | F86: =IFERROR('Cash Flow Data'!H18,0) -> 58 | G86: =IFERROR('Cash Flow Data'!I18,0) -> 620 | H86: =IFERROR('Cash Flow Data'!J18,0) -> 1797 | I86: =IFERROR('Cash Flow Data'!K18,0) -> 232 | J86: =IFERROR('Cash Flow Data'!L18,0) -> 21 | ... L86: =IFERROR('Cash Flow Data'!N18,0) -> 32
B87: Invest in subsidiaries | C87: =IFERROR('Cash Flow Data'!E19,0) -> 0 | D87: =IFERROR('Cash Flow Data'!F19,0) -> 0 | E87: =IFERROR('Cash Flow Data'!G19,0) -> 0 | F87: =IFERROR('Cash Flow Data'!H19,0) -> 0 | G87: =IFERROR('Cash Flow Data'!I19,0) -> 0 | H87: =IFERROR('Cash Flow Data'!J19,0) -> 0 | I87: =IFERROR('Cash Flow Data'!K19,0) -> 0 | J87: =IFERROR('Cash Flow Data'!L19,0) -> 0 | ... L87: =IFERROR('Cash Flow Data'!N19,0) -> 0
B88: Investment in group cos | C88: =IFERROR('Cash Flow Data'!E20,0) -> 0 | D88: =IFERROR('Cash Flow Data'!F20,0) -> 0 | E88: =IFERROR('Cash Flow Data'!G20,0) -> -160 | F88: =IFERROR('Cash Flow Data'!H20,0) -> 0 | G88: =IFERROR('Cash Flow Data'!I20,0) -> -107 | H88: =IFERROR('Cash Flow Data'!J20,0) -> -4 | I88: =IFERROR('Cash Flow Data'!K20,0) -> -9 | J88: =IFERROR('Cash Flow Data'!L20,0) -> -606 | ... L88: =IFERROR('Cash Flow Data'!N20,0) -> 0
B89: Redemp n Canc of Shares | C89: =IFERROR('Cash Flow Data'!E21,0) -> 0 | D89: =IFERROR('Cash Flow Data'!F21,0) -> 0 | E89: =IFERROR('Cash Flow Data'!G21,0) -> 0 | F89: =IFERROR('Cash Flow Data'!H21,0) -> 0 | G89: =IFERROR('Cash Flow Data'!I21,0) -> 0 | H89: =IFERROR('Cash Flow Data'!J21,0) -> 14 | I89: =IFERROR('Cash Flow Data'!K21,0) -> 533 | J89: =IFERROR('Cash Flow Data'!L21,0) -> 0 | ... L89: =IFERROR('Cash Flow Data'!N21,0) -> 0
B90: Acquisition of companies | C90: =IFERROR('Cash Flow Data'!E22,0) -> 0 | D90: =IFERROR('Cash Flow Data'!F22,0) -> -185 | E90: =IFERROR('Cash Flow Data'!G22,0) -> 0 | F90: =IFERROR('Cash Flow Data'!H22,0) -> -111 | G90: =IFERROR('Cash Flow Data'!I22,0) -> 0 | H90: =IFERROR('Cash Flow Data'!J22,0) -> 0 | I90: =IFERROR('Cash Flow Data'!K22,0) -> -8 | J90: =IFERROR('Cash Flow Data'!L22,0) -> -27 | ... L90: =IFERROR('Cash Flow Data'!N22,0) -> -98
B91: Inter corporate deposits | C91: =IFERROR('Cash Flow Data'!E23,0) -> 45 | D91: =IFERROR('Cash Flow Data'!F23,0) -> 0 | E91: =IFERROR('Cash Flow Data'!G23,0) -> 0 | F91: =IFERROR('Cash Flow Data'!H23,0) -> 0 | G91: =IFERROR('Cash Flow Data'!I23,0) -> 0 | H91: =IFERROR('Cash Flow Data'!J23,0) -> 0 | I91: =IFERROR('Cash Flow Data'!K23,0) -> 0 | J91: =IFERROR('Cash Flow Data'!L23,0) -> 0 | ... L91: =IFERROR('Cash Flow Data'!N23,0) -> 0
B92: Other investing items | C92: =IFERROR('Cash Flow Data'!E24,0) -> -5103 | D92: =IFERROR('Cash Flow Data'!F24,0) -> -1149 | E92: =IFERROR('Cash Flow Data'!G24,0) -> 456 | F92: =IFERROR('Cash Flow Data'!H24,0) -> -1289 | G92: =IFERROR('Cash Flow Data'!I24,0) -> -26663 | H92: =IFERROR('Cash Flow Data'!J24,0) -> 5360 | I92: =IFERROR('Cash Flow Data'!K24,0) -> 7335 | J92: =IFERROR('Cash Flow Data'!L24,0) -> -2659 | ... L92: =IFERROR('Cash Flow Data'!N24,0) -> 12813
B93: Cash from Investing Activities | C93: =IFERROR(SUM(C81:C92),0) -> -22969 | D93: =IFERROR(SUM(D81:D92),0) -> -27991 | E93: =IFERROR(SUM(E81:E92),0) -> -36233 | F93: =IFERROR(SUM(F81:F92),0) -> -36694 | G93: =IFERROR(SUM(G81:G92),0) -> -39572 | H93: =IFERROR(SUM(H81:H92),0) -> -25140 | I93: =IFERROR(SUM(I81:I92),0) -> -20879 | J93: =IFERROR(SUM(J81:J92),0) -> -33116 | ... L93: =IFERROR(SUM(L81:L92),0) -> -4442
B95: Financing Activities
B96: Proceeds from shares | C96: =IFERROR('Cash Flow Data'!E26,0) -> 1 | D96: =IFERROR('Cash Flow Data'!F26,0) -> 0 | E96: =IFERROR('Cash Flow Data'!G26,0) -> 0 | F96: =IFERROR('Cash Flow Data'!H26,0) -> 7433 | G96: =IFERROR('Cash Flow Data'!I26,0) -> 5 | H96: =IFERROR('Cash Flow Data'!J26,0) -> 0 | I96: =IFERROR('Cash Flow Data'!K26,0) -> 0 | J96: =IFERROR('Cash Flow Data'!L26,0) -> 3889 | ... L96: =IFERROR('Cash Flow Data'!N26,0) -> 19
B97: Redemption of debentures | C97: =IFERROR('Cash Flow Data'!E27,0) -> -97 | D97: =IFERROR('Cash Flow Data'!F27,0) -> -658 | E97: =IFERROR('Cash Flow Data'!G27,0) -> -744 | F97: =IFERROR('Cash Flow Data'!H27,0) -> 0 | G97: =IFERROR('Cash Flow Data'!I27,0) -> 0 | H97: =IFERROR('Cash Flow Data'!J27,0) -> 0 | I97: =IFERROR('Cash Flow Data'!K27,0) -> 0 | J97: =IFERROR('Cash Flow Data'!L27,0) -> 0 | ... L97: =IFERROR('Cash Flow Data'!N27,0) -> 0
B98: Proceeds from borrowings | C98: =IFERROR('Cash Flow Data'!E28,0) -> 27863 | D98: =IFERROR('Cash Flow Data'!F28,0) -> 33258 | E98: =IFERROR('Cash Flow Data'!G28,0) -> 36363 | F98: =IFERROR('Cash Flow Data'!H28,0) -> 19519 | G98: =IFERROR('Cash Flow Data'!I28,0) -> 33390 | H98: =IFERROR('Cash Flow Data'!J28,0) -> 37482 | I98: =IFERROR('Cash Flow Data'!K28,0) -> 51128 | J98: =IFERROR('Cash Flow Data'!L28,0) -> 38297 | ... L98: =IFERROR('Cash Flow Data'!N28,0) -> 46578
B99: Repayment of borrowings | C99: =IFERROR('Cash Flow Data'!E29,0) -> -20395 | D99: =IFERROR('Cash Flow Data'!F29,0) -> -29141 | E99: =IFERROR('Cash Flow Data'!G29,0) -> -23332 | F99: =IFERROR('Cash Flow Data'!H29,0) -> -24924 | G99: =IFERROR('Cash Flow Data'!I29,0) -> -21732 | H99: =IFERROR('Cash Flow Data'!J29,0) -> -29964 | I99: =IFERROR('Cash Flow Data'!K29,0) -> -35198 | J99: =IFERROR('Cash Flow Data'!L29,0) -> -29847 | ... L99: =IFERROR('Cash Flow Data'!N29,0) -> -42816
B100: Proceeds from deposits | C100: =IFERROR('Cash Flow Data'!E30,0) -> 0 | D100: =IFERROR('Cash Flow Data'!F30,0) -> 0 | E100: =IFERROR('Cash Flow Data'!G30,0) -> 0 | F100: =IFERROR('Cash Flow Data'!H30,0) -> 0 | G100: =IFERROR('Cash Flow Data'!I30,0) -> 0 | H100: =IFERROR('Cash Flow Data'!J30,0) -> 0 | I100: =IFERROR('Cash Flow Data'!K30,0) -> 0 | J100: =IFERROR('Cash Flow Data'!L30,0) -> 0 | ... L100: =IFERROR('Cash Flow Data'!N30,0) -> 0
B101: Interest paid fin | C101: =IFERROR('Cash Flow Data'!E31,0) -> -4666 | D101: =IFERROR('Cash Flow Data'!F31,0) -> -6171 | E101: =IFERROR('Cash Flow Data'!G31,0) -> -6307 | F101: =IFERROR('Cash Flow Data'!H31,0) -> -5716 | G101: =IFERROR('Cash Flow Data'!I31,0) -> -5336 | H101: =IFERROR('Cash Flow Data'!J31,0) -> -5411 | I101: =IFERROR('Cash Flow Data'!K31,0) -> -7005 | J101: =IFERROR('Cash Flow Data'!L31,0) -> -7518 | ... L101: =IFERROR('Cash Flow Data'!N31,0) -> -9251
B102: Dividends paid | C102: =IFERROR('Cash Flow Data'!E32,0) -> -1551 | D102: =IFERROR('Cash Flow Data'!F32,0) -> -722 | E102: =IFERROR('Cash Flow Data'!G32,0) -> -720 | F102: =IFERROR('Cash Flow Data'!H32,0) -> -108 | G102: =IFERROR('Cash Flow Data'!I32,0) -> -121 | H102: =IFERROR('Cash Flow Data'!J32,0) -> -96 | I102: =IFERROR('Cash Flow Data'!K32,0) -> -95 | J102: =IFERROR('Cash Flow Data'!L32,0) -> -57 | ... L102: =IFERROR('Cash Flow Data'!N32,0) -> -100
B103: Financial liabilities | C103: =IFERROR('Cash Flow Data'!E33,0) -> 0 | D103: =IFERROR('Cash Flow Data'!F33,0) -> 0 | E103: =IFERROR('Cash Flow Data'!G33,0) -> 0 | F103: =IFERROR('Cash Flow Data'!H33,0) -> 0 | G103: =IFERROR('Cash Flow Data'!I33,0) -> 0 | H103: =IFERROR('Cash Flow Data'!J33,0) -> 0 | I103: =IFERROR('Cash Flow Data'!K33,0) -> 0 | J103: =IFERROR('Cash Flow Data'!L33,0) -> -1346 | ... L103: =IFERROR('Cash Flow Data'!N33,0) -> -1559
B104: Other financing items | C104: =IFERROR('Cash Flow Data'!E34,0) -> -2849 | D104: =IFERROR('Cash Flow Data'!F34,0) -> -450 | E104: =IFERROR('Cash Flow Data'!G34,0) -> -57 | F104: =IFERROR('Cash Flow Data'!H34,0) -> 0 | G104: =IFERROR('Cash Flow Data'!I34,0) -> 0 | H104: =IFERROR('Cash Flow Data'!J34,0) -> 0 | I104: =IFERROR('Cash Flow Data'!K34,0) -> 0 | J104: =IFERROR('Cash Flow Data'!L34,0) -> -29 | ... L104: =IFERROR('Cash Flow Data'!N34,0) -> 3750
B105: Cash from Financing Activities | C105: =SUM(C96:C104) -> -1694 | D105: =SUM(D96:D104) -> -3884 | E105: =SUM(E96:E104) -> 5203 | F105: =SUM(F96:F104) -> -3796 | G105: =SUM(G96:G104) -> 6206 | H105: =SUM(H96:H104) -> 2011 | I105: =SUM(I96:I104) -> 8830 | J105: =SUM(J96:J104) -> 3389 | ... L105: =SUM(L96:L104) -> -3379
B107: Net Cash Flow | C107: =SUM(C78,C93,C105) -> -2504 | D107: =SUM(D78,D93,D105) -> 8433 | E107: =SUM(E78,E93,E105) -> 830 | F107: =SUM(F78,F93,F105) -> -1278 | G107: =SUM(G78,G93,G105) -> 88 | H107: =SUM(H78,H93,H105) -> -5706 | I107: =SUM(I78,I93,I105) -> -378 | J107: =SUM(J78,J93,J105) -> 1971 | ... L107: =SUM(L78,L93,L105) -> -4013

Sheet Cash Flow Data
C2: 40603 | D2: 40969 | E2: 41334 | F2: 41699 | G2: 42064 | H2: 42430 | I2: 42795 | J2: 43160 | K2: 43525 | L2: 43891 | M2: 44256 | N2: 44621
B3: Cash from Operating Activity - | C3: 11240 | D3: 18384 | E3: 22163 | F3: 36151 | G3: 35531 | H3: 37900 | I3: 30199 | J3: 23857 | K3: 18891 | L3: 26633 | M3: 29001 | N3: 14283
B4: Profit from operations | C4: 16680 | D4: 22432 | E4: 24406 | F4: 36303 | G4: 43397 | H4: 38626 | I4: 28840 | J4: 33312 | K4: 28771 | L4: 23352 | M4: 31198 | N4: 26666
B5: Receivables | C5: -1422 | D5: -6659 | E5: -5177 | F5: 445 | G5: -3179 | H5: -2223 | I5: -4152 | J5: -10688 | K5: -9109 | L5: 9950 | M5: -5505 | N5: 337
B6: Inventory | C6: -2411 | D6: -2719 | E6: -2656 | F6: -2853 | G6: -3692 | H6: -5743 | I6: -6621 | J6: -3560 | K6: 2069 | L6: 2326 | M6: 3814 | N6: 597
B7: Payables | C7: 344 | D7: 5867 | E7: 8132 | F7: 4694 | G7: 3598 | H7: 3947 | I7: 9301 | J7: 7320 | K7: -4692 | L7: -8085 | M7: 5748 | N7: -7012
B8: Loans Advances | C8: 0 | D8: 0 | E8: 0 | F8: 0 | G8: 0 | H8: -520 | I8: 0 | J8: 0 | K8: 0 | L8: 0 | M8: 0 | N8: 0
B9: Other WC items | C9: -559 | D9: 1231 | E9: -303 | F9: 1870 | G9: -398 | H9: 5852 | I9: 4727 | J9: 494 | K9: 4512 | L9: 875 | M9: -4150 | N9: -4396
B10: Working capital changes | C10: -4048 | D10: -2280 | E10: -3 | F10: 4157 | G10: -3672 | H10: 1313 | I10: 3254 | J10: -6434 | K10: -7221 | L10: 5065 | M10: -93 | N10: -10474
B11: Direct taxes | C11: -1391 | D11: -1768 | E11: -2240 | F11: -4308 | G11: -4194 | H11: -2040 | I11: -1895 | J11: -3021 | K11: -2659 | L11: -1785 | M11: -2105 | N11: -1910
B12: Cash from Investing Activity - | C12: -7023 | D12: -19464 | E12: -22969 | F12: -27991 | G12: -36232 | H12: -36694 | I12: -39571 | J12: -25139 | K12: -20878 | L12: -33115 | M12: -25672 | N12: -4444
B13: Fixed assets purchased | C13: -8124 | D13: -13876 | E13: -18863 | F13: -26975 | G13: -31962 | H13: -31503 | I13: -16072 | J13: -35079 | K13: -35304 | L13: -29702 | M13: -20205 | N13: -15168
B14: Fixed assets sold | C14: 11 | D14: 93 | E14: 37 | F14: 50 | G14: 74 | H14: 59 | I14: 53 | J14: 30 | K14: 67 | L14: 171 | M14: 351 | N14: 230
... B35: Net Cash Flow | C35: 2815 | D35: 5488 | E35: -2499 | F35: 4277 | G35: 4500 | H35: -2589 | I35: -3167 | J35: 730 | K35: 6843 | L35: -3092 | M35: 13232 | N35: 6459

Sheet Data Sheet
A1: COMPANY NAME | B1: INFOSYS LTD | E1: =IF(B2<>B3, "A NEW VERSION OF THE WORKSHEET IS AVAILABLE", "")
A2: LATEST VERSION | B2: 2.1 | E2: PLEASE DO NOT MAKE ANY CHANGES TO THIS SHEET
A3: CURRENT VERSION | B3: 2.1
A5: META
A6: Number of shares | B6: =IF(B9>0, B9/B8, 0) -> 405.41143
A7: Face Value | B7: 5
A8: Current Price | B8: 1174.5
A9: Market Capitalization | B9: 476155.72
A15: PROFIT & LOSS | B15: =B26+B34 -> 23357 | K15: =K17-K18-K20-K21-K22-K23-K19 -> 43609
A16: Report Date | B16: 42825 | C16: 43190 | D16: 43555 | E16: 43921 | F16: 44286 | G16: 44651 | H16: 45016 | I16: 45382 | J16: 45747 | K16: 46112
A17: Sales | B17: 68484 | C17: 70522 | D17: 82675 | E17: 90791 | F17: 100472 | G17: 121641 | H17: 146767 | I17: 153670 | J17: 162990 | K17: 178650
A18: Raw Material Cost
A19: Change in Inventory
A20: Power and Fuel | B20: 228 | C20: 207 | D20: 221 | E20: 229 | F20: 143 | G20: 132 | H20: 176 | I20: 199 | J20: 222 | K20: 223
A21: Other Mfr. Exp | B21: 6712 | C21: 7286 | D21: 9902 | E21: 11086 | F21: 12800 | G21: 20690 | H21: 26330 | I21: 27195 | J21: 30395 | K21: 32922
A22: Employee Cost | B22: 37669 | C22: 38902 | D22: 45323 | E22: 50895 | F22: 55547 | G22: 63997 | H22: 78374 | I22: 82636 | J22: 85968 | K22: 95112
A23: Selling and admin | B23: 4584 | C23: 4585 | D23: 5553 | E23: 5375 | F23: 3194 | G23: 4305 | H23: 5300 | I23: 5705 | J23: 6039 | K23: 6784
A24: Other Expenses | B24: 687 | C24: 720 | D24: 1506 | E24: 939 | F24: 899 | G24: 1026 | H24: 1457 | I24: 1510 | J24: 1130 | K24: 1329
A25: Other Income | B25: 3050 | C25: 3311 | D25: 2882 | E25: 2803 | F25: 2201 | G25: 2295 | H25: 2701 | I25: 4711 | J25: 3600 | K25: 3033
A26: Depreciation | B26: 1703 | C26: 1863 | D26: 2011 | E26: 2893 | F26: 3267 | G26: 3476 | H26: 4225 | I26: 4678 | J26: 4812 | K26: 4902
A27: Interest | E27: 170 | F27: 195 | G27: 200 | H27: 284 | I27: 470 | J27: 416 | K27: 416
A28: Profit before tax | B28: 19951 | C28: 20270 | D28: 21041 | E28: 22007 | F28: 26628 | G28: 30110 | H28: 33322 | I28: 35988 | J28: 37608 | K28: 39995
A29: Tax | B29: 5598 | C29: 4241 | D29: 5631 | E29: 5368 | F29: 7205 | G29: 7964 | H29: 9214 | I29: 9740 | J29: 10858 | K29: 10521
A30: Net profit | B30: 14353 | C30: 16029 | D30: 15404 | E30: 16594 | F30: 19351 | G30: 22110 | H30: 24095 | I30: 26233 | J30: 26713 | K30: 29440
A31: Dividend Amount | B31: 5891.6 | C31: 9465.6 | D31: 9222.5 | E31: 7427 | F31: 11469.6 | G31: 13007.6 | H31: 14069.2 | I31: 19053.2 | J31: 17827.8 | K31: 19430.4
A32: Effective Tax Rate | B32: =B29/B28 -> 0.28058744 | C32: =C29/C28 -> 0.20922546 | D32: =D29/D28 -> 0.26762036 | E32: =E29/E28 -> 0.24392239 | F32: =F29/F28 -> 0.27057984 | G32: =G29/G28 -> 0.26449684 | H32: =H29/H28 -> 0.27651401 | I32: =I29/I28 -> 0.27064577 | ... K32: =K29/K28 -> 0.26305788
A34: EBITDA | B34: =+B30+B29+B27+B26 -> 21654 | C34: =+C30+C29+C27+C26 -> 22133 | D34: =+D30+D29+D27+D26 -> 23046 | E34: =+E30+E29+E27+E26 -> 25025 | F34: =+F30+F29+F27+F26 -> 30018 | G34: =+G30+G29+G27+G26 -> 33750 | H34: =+H30+H29+H27+H26 -> 37818 | I34: =+I30+I29+I27+I26 -> 41121 | ... K34: =+K30+K29+K27+K26 -> 45279
A40: Quarters
A41: Report Date | B41: 45291 | C41: 45382 | D41: 45473 | E41: 45565 | F41: 45657 | G41: 45747 | H41: 45838 | I41: 45930 | J41: 46022 | K41: 46112
A42: Sales | B42: 38821 | C42: 37923 | D42: 39315 | E42: 40986 | F42: 41764 | G42: 40925 | H42: 42279 | I42: 44490 | J42: 45479 | K42: 46402
A43: Expenses | B43: 29684 | C43: 29139 | D43: 29878 | E43: 31177 | F43: 31649 | G43: 31051 | H43: 32336 | I43: 33955 | J43: 34845 | K43: 35235
A44: Other Income | B44: 789 | C44: 2729 | D44: 838 | E44: 712 | F44: 859 | G44: 1190 | H44: 1042 | I44: 982 | J44: -150 | K44: 1159
A45: Depreciation | B45: 1176 | C45: 1163 | D45: 1149 | E45: 1160 | F45: 1203 | G45: 1299 | H45: 1140 | I45: 1182 | J45: 1155 | K45: 1424
A46: Interest | B46: 131 | C46: 110 | D46: 105 | E46: 108 | F46: 101 | G46: 102 | H46: 105 | I46: 106 | J46: 100 | K46: 105
A47: Profit before tax | B47: 8619 | C47: 10240 | D47: 9021 | E47: 9253 | F47: 9670 | G47: 9663 | H47: 9740 | I47: 10229 | J47: 9229 | K47: 10797
A48: Tax | B48: 2506 | C48: 2265 | D48: 2647 | E48: 2737 | F48: 2848 | G48: 2625 | H48: 2816 | I48: 2854 | J48: 2563 | K48: 2288
A49: Net profit | B49: 6106 | C49: 7969 | D49: 6368 | E49: 6506 | F49: 6806 | G49: 7033 | H49: 6921 | I49: 7364 | J49: 6654 | K49: 8501
A50: Operating Profit | B50: 9137 | C50: 8784 | D50: 9437 | E50: 9809 | F50: 10115 | G50: 9874 | H50: 9943 | I50: 10535 | J50: 10634 | K50: 11167
A51: EBITDA | B51: =B49+B48+B46+B45 -> 9919 | C51: =C49+C48+C46+C45 -> 11507 | D51: =D49+D48+D46+D45 -> 10269 | E51: =E49+E48+E46+E45 -> 10511 | F51: =F49+F48+F46+F45 -> 10958 | G51: =G49+G48+G46+G45 -> 11059 | H51: =H49+H48+H46+H45 -> 10982 | I51: =I49+I48+I46+I45 -> 11506 | ... K51: =K49+K48+K46+K45 -> 12318
A55: BALANCE SHEET
A56: Report Date | B56: 42825 | C56: 43190 | D56: 43555 | E56: 43921 | F56: 44286 | G56: 44651 | H56: 45016 | I56: 45382 | J56: 45747 | K56: 46112
A57: Equity Share Capital | B57: 1144 | C57: 1088 | D57: 2170 | E57: 2122 | F57: 2124 | G57: 2098 | H57: 2069 | I57: 2071 | J57: 2073 | K57: 2024
A58: Reserves | B58: 67838 | C58: 63835 | D58: 62778 | E58: 63328 | F58: 74227 | G58: 73252 | H58: 73338 | I58: 86045 | J58: 93745 | K58: 90828
A59: Borrowings | E59: 4633 | F59: 5325 | G59: 5474 | H59: 8299 | I59: 8359 | J59: 8227 | K59: 9176
A60: Other Liabilities | B60: 14166 | C60: 14426 | D60: 19118 | E60: 21717 | F60: 25835 | G60: 35905 | H60: 40890 | I60: 40885 | J60: 43750 | K60: 52260
A61: Total | B61: 83148 | C61: 79349 | D61: 84066 | E61: 91800 | F61: 107511 | G61: 116729 | H61: 124596 | I61: 137360 | J61: 147795 | K61: 154288
A62: Net Block | B62: 14179 | C62: 12574 | D62: 15710 | E62: 23789 | F62: 25505 | G62: 25800 | H62: 29225 | I62: 27622 | J62: 30961 | K62: 33770
A63: Capital Work in Progress | B63: 1365 | C63: 1606 | D63: 1388 | E63: 954 | F63: 922 | G63: 416 | H63: 288 | I63: 293 | J63: 814 | K63: 526
A64: Investments | B64: 16423 | C64: 12163 | D64: 11261 | E64: 8792 | F64: 14205 | G64: 20324 | H64: 19478 | I64: 24623 | J64: 23541 | K64: 21880
A65: Other Assets | B65: 51181 | C65: 53006 | D65: 55707 | E65: 58265 | F65: 66879 | G65: 70189 | H65: 75605 | I65: 84822 | J65: 92479 | K65: 98112
A66: Total | B66: 83148 | C66: 79349 | D66: 84066 | E66: 91800 | F66: 107511 | G66: 116729 | H66: 124596 | I66: 137360 | J66: 147795 | K66: 154288
A67: Receivables | B67: 12322 | C67: 13142 | D67: 14827 | E67: 18487 | F67: 19294 | G67: 22698 | H67: 25424 | I67: 30193 | J67: 31158 | K67: 35234
A68: Inventory
A69: Cash & Bank | B69: 22625 | C69: 19818 | D69: 19568 | E69: 18649 | F69: 24714 | G69: 17472 | H69: 12173 | I69: 14786 | J69: 24455 | K69: 22201
A70: No. of Equity Shares | B70: 2285655150 | C70: 2173312301 | D70: 4335954462 | E70: 4240753210 | F70: 4245146114 | G70: 4193012929 | H70: 4136387925 | I70: 4139950635 | J70: 4143607528 | K70: 4046940812
A71: New Bonus Shares | D71: 2184191490
A72: Face value | B72: 5 | C72: 5 | D72: 5 | E72: 5 | F72: 5 | G72: 5 | H72: 5 | I72: 5 | J72: 5 | K72: 5
H73: =H62-G62+H45 -> 4565 | I73: =I62-H62+I45 -> -421 | J73: =J62-I62+J45 -> 4494 | K73: =K62-J62+K45 -> 4233
A80: CASH FLOW:
A81: Report Date | B81: 42825 | C81: 43190 | D81: 43555 | E81: 43921 | F81: 44286 | G81: 44651 | H81: 45016 | I81: 45382 | J81: 45747 | K81: 46112
A82: Cash from Operating Activity | B82: 11531 | C82: 13218 | D82: 14841 | E82: 17003 | F82: 23224 | G82: 23885 | H82: 22467 | I82: 25210 | J82: 35694 | K82: 33986
A83: Cash from Investing Activity | B83: -14664 | C83: 4533 | D83: -632 | E83: -331 | F83: -7373 | G83: -6485 | H83: -1071 | I83: -5093 | J83: -1864 | K83: 3546
A84: Cash from Financing Activity | B84: -6939 | C84: -20505 | D84: -14512 | E84: -17591 | F84: -9786 | G84: -24642 | H84: -26695 | I84: -17504 | J84: -24161 | K84: -39786
A85: Net Cash Flow | B85: -10072 | C85: -2754 | D85: -303 | E85: -919 | F85: 6065 | G85: -7242 | H85: -5299 | I85: 2613 | J85: 9669 | K85: -2254
A90: PRICE: | B90: 511.13 | C90: 565.9 | D90: 743.85 | E90: 641.5 | F90: 1368.05 | G90: 1906.85 | H90: 1427.95 | I90: 1498.05 | J90: 1570.65 | K90: 1250.6
A92: DERIVED:
A93: Adjusted Equity Shares in Cr | B93: 459.39 | C93: 436.82 | D93: 436.89 | E93: 425.9 | F93: 426.07 | G93: 420.67 | H93: 414.86 | I93: 415.09 | J93: 415.33 | K93: 405.56

Sheet ASSUMPTIONS
B1: Infosys Ltd - Key Assumptions
B2: WACC (Discount Rate) | F2: 0.11 | G2: CAPM: Riskfree rate 6% , Market risk 12% with a beta of 0.75
B3: Terminal Growth Rate | F3: 0.05 | G3: Nominal growth rate of GDP in India
B4: Forecast Horizon (years) | F4: 5 years
B5: Revenue Growth – FY27 | F5: 0.11
B6: Revenue Growth – FY28 | F6: 0.1
B7: Revenue Growth – FY29 | F7: 0.09
B8: Revenue Growth – FY30 | F8: 0.08
B9: Revenue Growth – FY31 | F9: 0.07
B10: EBITDA Margin – FY27 | F10: 0.28
B11: EBITDA Margin – FY28 | F11: 0.285
B12: EBITDA Margin – FY29 | F12: 0.29
B13: EBITDA Margin – FY30 | F13: 0.295
B14: EBITDA Margin – FY31 | F14: 0.3
B15: Depreciation % of Revenue | F15: 0.029 | G15: Average of past 5 years
B16: CapEx % of Revenue | F16: 0.02
B17: Change in NWC % of Rev | F17: 0.01
B18: Effective Tax Rate | F18: 0.3 | G18: Average of past 5 years
B19: Net Debt (FY26, ₹ Cr) | F19: -13025 | G19: Cash>Debt, that's why negative value

Sheet DCF VALUATION
B1: DCF VALUATION - INFOSYS LTD (all values in Rs CR. except per share value) | Q1: Infosys Ltd - Key Assumptions
A2: # | B2: Line Item | C2: FY26A | D2: FY27E | E2: FY28E | F2: FY29E | G2: FY30E | H2: FY31E
B3: Revenue (₹ Cr) | C3: ='Financials>'!L5 -> 178650 | D3: =C3*(1+R6) -> 198301.5 | E3: =D3*(1+R7) -> 218131.65 | F3: =E3*(1+R8) -> 237763.5 | G3: =F3*(1+R9) -> 256784.58 | H3: =G3*(1+R10) -> 274759.5 | P3: # | Q3: WACC (Discount Rate) | R3: =ASSUMPTIONS!F2 -> 0.11
B4: Revenue Growth % | C4: ='Financials>'!L6 -> 0.096079514 | D4: =R6 -> 0.11 | E4: =R7 -> 0.1 | F4: =R8 -> 0.09 | G4: =R9 -> 0.08 | H4: =R10 -> 0.07 | Q4: Terminal Growth Rate | R4: =ASSUMPTIONS!F3 -> 0.05
B5: EBITDA (₹ Cr) | C5: ='Financials>'!L17 -> 42280 | D5: =D3*D6 -> 55524.42 | E5: =E3*E6 -> 62167.52 | F5: =F3*F6 -> 68951.415 | G5: =G3*G6 -> 75751.451 | H5: =H3*H6 -> 82427.85 | Q5: Forecast Horizon (years) | R5: =ASSUMPTIONS!F4 -> 5 years
B6: EBITDA Margin % | C6: ='Financials>'!L18 -> 0.23666387 | D6: =R11 -> 0.28 | E6: =R12 -> 0.285 | F6: =R13 -> 0.29 | G6: =R14 -> 0.295 | H6: =R15 -> 0.3 | Q6: Revenue Growth – FY27 | R6: =ASSUMPTIONS!F5 -> 0.11
B7: (-) Depreciation (₹ Cr) | C7: ='Financials>'!L23 -> 4902 | D7: =$R$16*D3 -> 5750.7435 | E7: =$R$16*E3 -> 6325.8179 | F7: =$R$16*F3 -> 6895.1415 | G7: =$R$16*G3 -> 7446.7528 | H7: =$R$16*H3 -> 7968.0255 | Q7: Revenue Growth – FY28 | R7: =ASSUMPTIONS!F6 -> 0.1
B8: EBIT (₹ Cr) | C8: ='DCF VALUATION'!C5-'DCF VALUATION'!C7 -> 37378 | D8: =D5-D7 -> 49773.677 | E8: =E5-E7 -> 55841.702 | F8: =F5-F7 -> 62056.273 | G8: =G5-G7 -> 68304.698 | H8: =H5-H7 -> 74459.824 | Q8: Revenue Growth – FY29 | R8: =ASSUMPTIONS!F7 -> 0.09
B9: NOPAT = EBIT×(1-Tax) | C9: =C8*(1-R19) -> 26164.6 | D9: =D8*(1-$R$19) -> 34841.574 | E9: =E8*(1-$R$19) -> 39089.192 | F9: =F8*(1-$R$19) -> 43439.391 | G9: =G8*(1-$R$19) -> 47813.288 | H9: =H8*(1-$R$19) -> 52121.877 | Q9: Revenue Growth – FY30 | R9: =ASSUMPTIONS!F8 -> 0.08
B10: (+) Depreciation (₹ Cr) | C10: ='Financials>'!L23 -> 4902 | D10: =D7 -> 5750.7435 | E10: =E7 -> 6325.8179 | F10: =F7 -> 6895.1415 | G10: =G7 -> 7446.7528 | H10: =H7 -> 7968.0255 | I10: =I7 -> 0 | Q10: Revenue Growth – FY31 | R10: =ASSUMPTIONS!F9 -> 0.07
B11: (-) CapEx (₹ Cr) | C11: =2%*C3 -> 3573 | D11: =$R$17*D3 -> 3966.03 | E11: =$R$17*E3 -> 4362.633 | F11: =$R$17*F3 -> 4755.27 | G11: =$R$17*G3 -> 5135.6916 | H11: =$R$17*H3 -> 5495.19 | Q11: EBITDA Margin – FY27 | R11: =ASSUMPTIONS!F10 -> 0.28
B12: (-) Chg in NWC (₹ Cr) | C12: =$R$18*C3 -> 1786.5 | D12: =$R$18*D3 -> 1983.015 | E12: =$R$18*E3 -> 2181.3165 | F12: =$R$18*F3 -> 2377.635 | G12: =$R$18*G3 -> 2567.8458 | H12: =$R$18*H3 -> 2747.595 | Q12: EBITDA Margin – FY28 | R12: =ASSUMPTIONS!F11 -> 0.285
B13: Free Cash Flow to Firm (FCFF) | C13: =C9+C10-C11-C12 -> 25707.1 | D13: =D9+D10-D11-D12 -> 34643.272 | E13: =E9+E10-E11-E12 -> 38871.06 | F13: =F9+F10-F11-F12 -> 43201.628 | G13: =G9+G10-G11-G12 -> 47556.504 | H13: =H9+H10-H11-H12 -> 51847.117 | Q13: EBITDA Margin – FY29 | R13: =ASSUMPTIONS!F12 -> 0.29
Q14: EBITDA Margin – FY30 | R14: =ASSUMPTIONS!F13 -> 0.295
A15: # | B15: Discounting and terminal value | Q15: EBITDA Margin – FY31 | R15: =ASSUMPTIONS!F14 -> 0.3
B16: Discount Factor (1/(1+WACC)^t) | C16: =(1/(1+$R$3)^0) -> 1 | D16: =(1/(1+$R$3)^1) -> 0.9009009 | E16: =(1/(1+$R$3)^2) -> 0.81162243 | F16: =(1/(1+$R$3)^3) -> 0.73119138 | G16: =(1/(1+$R$3)^4) -> 0.65873097 | H16: =(1/(1+$R$3)^5) -> 0.59345133 | Q16: Depreciation % of Revenue | R16: =ASSUMPTIONS!F15 -> 0.029
B17: PV of FCFF (₹ Cr) | C17: =C13*C16 -> 25707.1 | D17: =D13*D16 -> 31210.155 | E17: =E13*E16 -> 31548.624 | F17: =F13*F16 -> 31588.658 | G17: =G13*G16 -> 31326.942 | H17: =H13*H16 -> 30768.741 | Q17: CapEx % of Revenue | R17: =ASSUMPTIONS!F16 -> 0.02
B18: Sum of PV (FCFF) – 5 years | C18: =SUM(D17:H17) -> 156443.12 | Q18: Change in NWC % of Rev | R18: =ASSUMPTIONS!F17 -> 0.01
B19: Terminal FCFF (FY32E, ₹ Cr) | C19: =H13*(1+R4) -> 54439.473 | Q19: Effective Tax Rate | R19: =ASSUMPTIONS!F18 -> 0.3
B20: Terminal Value (Gordon Growth, ₹ Cr) | C20: =C19/(R3-R4) -> 907324.56 | Q20: Net Debt (FY26, ₹ Cr) | R20: =ASSUMPTIONS!F19 -> -13025
B21: PV of Terminal Value (₹ Cr) | C21: =C20/(1+R3)^5 -> 538452.96
A23: # | B23: Enterprise value, Equity value and Fair Value
B24: Enterprise Value (₹ Cr) | C24: =C21+C18 -> 694896.08
B25: (–) Net Debt (₹ Cr) | C25: =R20 -> -13025
B26: Equity Value (₹ Cr) | C26: =C24-C25 -> 707921.08
B27: Shares Outstanding (Crore) | C27: ='Data Sheet'!B6 -> 405.41143
B28: FAIR VALUE PER SHARE (₹) | C28: =C26/C27 -> 1746.1794
B29: Current Market Price (₹) | C29: ='Data Sheet'!B8 -> 1174.5
B30: Upside / (Downside) vs CMP | C30: =(C28-C29)/C29 -> 0.48674279
B31: Terminal Value as % of EV | C31: =C21/C24 -> 0.77486832

Sheet SENSITIVITY ANALYSIS
B2: SENSITIVITY ANALYSIS – FAIR VALUE PER SHARE (₹)
B4: Table : Fair Value vs WACC & Terminal Growth Rate
B5: WACC → / TGR ↓ | D5: 0.095 | E5: 0.105 | F5: 0.11 | G5: 0.115 | H5: 0.125 | I5: 0.135
B6: TGR = 3.0% | D6: 1721.43 | E6: 1489.36 | F6: 1395.16 | G6: 1312.1 | H6: 1172.33 | I6: 1059.34
B7: TGR = 3.5% | D7: 1835.48 | E7: 1571.06 | F7: 1465.37 | G7: 1372.94 | H7: 1219.02 | I7: 1096.04
B8: TGR = 4.0% | D8: 1970.26 | E8: 1665.32 | F8: 1545.6 | G8: 1441.89 | H8: 1271.21 | I8: 1136.6
B9: TGR = 4.5% | D9: 2132 | E9: 1775.29 | F9: 1638.17 | G9: 1520.7 | H9: 1329.91 | I9: 1181.67
B10: TGR = 5.0% | D10: 2329.68 | E10: 1905.26 | F10: 1746.18 | G10: 1611.62 | H10: 1396.45 | I10: 1232.03
B11: TGR = 5.5% | D11: 2576.77 | E11: 2061.22 | F11: 1873.82 | G11: 1717.7 | H11: 1472.48 | I11: 1288.7
B12: TGR = 6.0% | D12: 2894.47 | E12: 2251.84 | F12: 2026.99 | G12: 1843.07 | H12: 1560.22 | I12: 1352.92
